{
"companyName": "DefaultCompany",
"productName": "face-tracking-face-mesh",
"productVersion": "0.1",
"dataUrl": "9d5491145d3d41f3a25d4608fbb732d8.unityweb",
"wasmCodeUrl": "fd4c0cf4455924a43b3398aa7ba80be3.unityweb",
"wasmFrameworkUrl": "a072447be521d40fb91333b5216066f5.unityweb",
"graphicsAPI": ["WebGL 2.0","WebGL 1.0"],
"webglContextAttributes": {"preserveDrawingBuffer": false},
"splashScreenStyle": "Dark",
"backgroundColor": "#231F20",
"cacheControl": {"default": "must-revalidate"},
"developmentBuild": false,
"multithreading": false,
"unityVersion": "2019.4.40f1"
}